atraxi_flow/__init__.py
atraxi_flow-99.99.99.dist-info/licenses/LICENSE
atraxi_flow-99.99.99.dist-info/METADATA
atraxi_flow-99.99.99.dist-info/WHEEL
atraxi_flow-99.99.99.dist-info/top_level.txt
atraxi_flow-99.99.99.dist-info/RECORD
